asyncadder.sv
//new module to test Async capabilities of testbench

module asyncadder #(parameter WIDTH1=8)(input wire [WIDTH1-1:0] a,
input wire [WIDTH1-1:0] b, output reg [WIDTH1:0] y);

    always @(*) begin
        y=a+b;
    end
endmodule

waveform1.vcd
$version Generated by VerilatedVcd $end
$date Fri Sep  9 16:48:30 2022 $end
$timescale 1ps $end

 $scope module TOP $end
  $var wire  8 # a [7:0] $end
  $var wire  8 $ b [7:0] $end
  $var wire  9 % y [8:0] $end
  $scope module asyncadder $end
   $var wire 32 & WIDTH1 [31:0] $end
   $var wire  8 # a [7:0] $end
   $var wire  8 $ b [7:0] $end
   $var wire  9 % y [8:0] $end
  $upscope $end
 $upscope $end
$enddefinitions $end


#0
b10100011 #
b10010111 $
b100111010 %
b00000000000000000000000000001000 &
#1
b10100010 #
b01010101 $
b011110111 %
#2
b01010011 #
b10111110 $
b100010001 %
#3
b11110001 #
b11111100 $
b111101101 %
#4
b11111001 #
b01111001 $
b101110010 %
#5
b01101011 #
b01010010 $
b010111101 %
#6
b00010100 #
b00010011 $
b000100111 %
#7
b11101001 #
b11100010 $
b111001011 %
#8
b00101101 #
b01010001 $
b001111110 %
#9
b10001110 #
b00011111 $
b010101101 %
#10
b01010110 #
b00001000 $
b001011110 %
#11
b01010111 #
b00100111 $
b001111110 %
#12
b10100111 #
b00000101 $
b010101100 %
#13
b11010100 #
b11010000 $
b110100100 %
#14
b01010010 #
b10000010 $
b011010100 %
#15
b01110111 #
b01110101 $
b011101100 %
#16
b00011011 #
b10011001 $
b010110100 %
#17
b01001010 #
b11101101 $
b100110111 %
#18
b01011000 #
b00111101 $
b010010101 %
#19
b01101010 #
b01010010 $
b010111100 %
#20
b00110110 #
b11010101 $
b100001011 %
#21
b00100100 #
b01001010 $
b001101110 %
#22
b01101000 #
b10001110 $
b011110110 %
#23
b10101101 #
b10010101 $
b101000010 %
#24
b01011111 #
b00111100 $
b010011011 %
#25
b00110101 #
b10110101 $
b011101010 %
#26
b11000100 #
b10001100 $
b101010000 %
#27
b11011101 #
b01101100 $
b101001001 %
#28
b00010001 #
b00110010 $
b001000011 %
#29
b00111101 #
b11100010 $
b100011111 %
#30
b10110100 #
b10110100 $
b101101000 %
#31
b01011001 #
b11111100 $
b101010101 %
